{
  "queries": [
    {
      "compatibility": {
        "android": {
          "28": {
            "reason": "No exact API semantic fixture; runtime capability proof required",
            "status": "capability_gated"
          },
          "29": {
            "reason": "No exact API semantic fixture; runtime capability proof required",
            "status": "capability_gated"
          },
          "30": {
            "reason": "No exact API semantic fixture; runtime capability proof required",
            "status": "capability_gated"
          },
          "31": {
            "reason": "No exact API semantic fixture; runtime capability proof required",
            "status": "capability_gated"
          },
          "32": {
            "reason": "No exact API semantic fixture; runtime capability proof required",
            "status": "capability_gated"
          },
          "33": {
            "reason": "No exact API semantic fixture; runtime capability proof required",
            "status": "capability_gated"
          },
          "34": {
            "reason": "No exact API semantic fixture; runtime capability proof required",
            "status": "capability_gated"
          },
          "35": {
            "reason": "No exact API semantic fixture; runtime capability proof required",
            "status": "capability_gated"
          },
          "36": {
            "reason": "No exact API semantic fixture; runtime capability proof required",
            "status": "capability_gated"
          },
          "37": {
            "reason": "No exact API semantic fixture; runtime capability proof required",
            "status": "capability_gated"
          }
        },
        "probe_capabilities": []
      },
      "id": "cpu_profiling/cpu_usage_overview",
      "license": {
        "origin": "smartperfetto",
        "spdx": "AGPL-3.0-or-later"
      },
      "path": "sql/cpu_profiling/cpu_usage_overview.sql",
      "sha256": "aa7d8a5fe7ad08e02be41283bd03fe1163a0d0095fe9771d49c91b94be5588c7",
      "signal_patterns": [],
      "skill_id": "cpu_profiling",
      "source": {
        "commit": "6333623a96295c1ad76e28bf1f5eb7a9ecd39864",
        "path": "backend/skills/deep/cpu_profiling.skill.yaml",
        "repository": "https://github.com/Gracker/SmartPerfetto",
        "sha256": "747b9f8972708ad1e4c8449ab8e9876c58138f44ae4f3515d87232a9173a4772"
      },
      "sql_dependencies": {
        "creates": [],
        "declared_modules": [
          "linux.cpu.frequency"
        ],
        "drops": [],
        "required_tables": [],
        "requires": [
          "_cpu_topology"
        ],
        "setup_queries": [
          "cpu_topology_view/create_topology_view"
        ]
      },
      "step_id": "cpu_usage_overview",
      "template": {
        "fragments": [],
        "parameters": [],
        "result_dependencies": []
      },
      "validation": {
        "default_execution": "capability_gate_required",
        "execution_verified": false,
        "fixtures": [],
        "runtime_compatible": null,
        "semantic_verified": false,
        "static_valid": true
      }
    },
    {
      "compatibility": {
        "android": {
          "28": {
            "reason": "No exact API semantic fixture; runtime capability proof required",
            "status": "capability_gated"
          },
          "29": {
            "reason": "No exact API semantic fixture; runtime capability proof required",
            "status": "capability_gated"
          },
          "30": {
            "reason": "No exact API semantic fixture; runtime capability proof required",
            "status": "capability_gated"
          },
          "31": {
            "reason": "No exact API semantic fixture; runtime capability proof required",
            "status": "capability_gated"
          },
          "32": {
            "reason": "No exact API semantic fixture; runtime capability proof required",
            "status": "capability_gated"
          },
          "33": {
            "reason": "No exact API semantic fixture; runtime capability proof required",
            "status": "capability_gated"
          },
          "34": {
            "reason": "No exact API semantic fixture; runtime capability proof required",
            "status": "capability_gated"
          },
          "35": {
            "reason": "No exact API semantic fixture; runtime capability proof required",
            "status": "capability_gated"
          },
          "36": {
            "reason": "No exact API semantic fixture; runtime capability proof required",
            "status": "capability_gated"
          },
          "37": {
            "reason": "No exact API semantic fixture; runtime capability proof required",
            "status": "capability_gated"
          }
        },
        "probe_capabilities": []
      },
      "id": "cpu_profiling/process_cpu_time",
      "license": {
        "origin": "smartperfetto",
        "spdx": "AGPL-3.0-or-later"
      },
      "path": "sql/cpu_profiling/process_cpu_time.sql",
      "sha256": "59554a6dd04b0d01f6ad9e849aec37de0621f0a34916c7e6fba930ee4f70ad8c",
      "signal_patterns": [
        "${package}*"
      ],
      "skill_id": "cpu_profiling",
      "source": {
        "commit": "6333623a96295c1ad76e28bf1f5eb7a9ecd39864",
        "path": "backend/skills/deep/cpu_profiling.skill.yaml",
        "repository": "https://github.com/Gracker/SmartPerfetto",
        "sha256": "747b9f8972708ad1e4c8449ab8e9876c58138f44ae4f3515d87232a9173a4772"
      },
      "sql_dependencies": {
        "creates": [],
        "declared_modules": [
          "linux.cpu.frequency"
        ],
        "drops": [],
        "required_tables": [],
        "requires": [],
        "setup_queries": []
      },
      "step_id": "process_cpu_time",
      "template": {
        "fragments": [],
        "parameters": [
          "min_runtime_ms",
          "package"
        ],
        "result_dependencies": []
      },
      "validation": {
        "default_execution": "capability_gate_required",
        "execution_verified": false,
        "fixtures": [],
        "runtime_compatible": null,
        "semantic_verified": false,
        "static_valid": true
      }
    },
    {
      "compatibility": {
        "android": {
          "28": {
            "reason": "No exact API semantic fixture; runtime capability proof required",
            "status": "capability_gated"
          },
          "29": {
            "reason": "No exact API semantic fixture; runtime capability proof required",
            "status": "capability_gated"
          },
          "30": {
            "reason": "No exact API semantic fixture; runtime capability proof required",
            "status": "capability_gated"
          },
          "31": {
            "reason": "No exact API semantic fixture; runtime capability proof required",
            "status": "capability_gated"
          },
          "32": {
            "reason": "No exact API semantic fixture; runtime capability proof required",
            "status": "capability_gated"
          },
          "33": {
            "reason": "No exact API semantic fixture; runtime capability proof required",
            "status": "capability_gated"
          },
          "34": {
            "reason": "No exact API semantic fixture; runtime capability proof required",
            "status": "capability_gated"
          },
          "35": {
            "reason": "No exact API semantic fixture; runtime capability proof required",
            "status": "capability_gated"
          },
          "36": {
            "reason": "No exact API semantic fixture; runtime capability proof required",
            "status": "capability_gated"
          },
          "37": {
            "reason": "No exact API semantic fixture; runtime capability proof required",
            "status": "capability_gated"
          }
        },
        "probe_capabilities": []
      },
      "id": "cpu_profiling/thread_cpu_time",
      "license": {
        "origin": "smartperfetto",
        "spdx": "AGPL-3.0-or-later"
      },
      "path": "sql/cpu_profiling/thread_cpu_time.sql",
      "sha256": "e12a78fe8b6173888e2f4ce31ad2fb4e2d30c875d6e4896228b303c65e5f2c77",
      "signal_patterns": [
        "${package}*"
      ],
      "skill_id": "cpu_profiling",
      "source": {
        "commit": "6333623a96295c1ad76e28bf1f5eb7a9ecd39864",
        "path": "backend/skills/deep/cpu_profiling.skill.yaml",
        "repository": "https://github.com/Gracker/SmartPerfetto",
        "sha256": "747b9f8972708ad1e4c8449ab8e9876c58138f44ae4f3515d87232a9173a4772"
      },
      "sql_dependencies": {
        "creates": [],
        "declared_modules": [
          "linux.cpu.frequency"
        ],
        "drops": [],
        "required_tables": [],
        "requires": [],
        "setup_queries": []
      },
      "step_id": "thread_cpu_time",
      "template": {
        "fragments": [],
        "parameters": [
          "min_runtime_ms",
          "package"
        ],
        "result_dependencies": []
      },
      "validation": {
        "default_execution": "capability_gate_required",
        "execution_verified": false,
        "fixtures": [],
        "runtime_compatible": null,
        "semantic_verified": false,
        "static_valid": true
      }
    },
    {
      "compatibility": {
        "android": {
          "28": {
            "reason": "No exact API semantic fixture; runtime capability proof required",
            "status": "capability_gated"
          },
          "29": {
            "reason": "No exact API semantic fixture; runtime capability proof required",
            "status": "capability_gated"
          },
          "30": {
            "reason": "No exact API semantic fixture; runtime capability proof required",
            "status": "capability_gated"
          },
          "31": {
            "reason": "No exact API semantic fixture; runtime capability proof required",
            "status": "capability_gated"
          },
          "32": {
            "reason": "No exact API semantic fixture; runtime capability proof required",
            "status": "capability_gated"
          },
          "33": {
            "reason": "No exact API semantic fixture; runtime capability proof required",
            "status": "capability_gated"
          },
          "34": {
            "reason": "No exact API semantic fixture; runtime capability proof required",
            "status": "capability_gated"
          },
          "35": {
            "reason": "No exact API semantic fixture; runtime capability proof required",
            "status": "capability_gated"
          },
          "36": {
            "reason": "No exact API semantic fixture; runtime capability proof required",
            "status": "capability_gated"
          },
          "37": {
            "reason": "No exact API semantic fixture; runtime capability proof required",
            "status": "capability_gated"
          }
        },
        "probe_capabilities": []
      },
      "id": "cpu_profiling/core_distribution",
      "license": {
        "origin": "smartperfetto",
        "spdx": "AGPL-3.0-or-later"
      },
      "path": "sql/cpu_profiling/core_distribution.sql",
      "sha256": "4b94dee2d868f672629be6af6c1891c1b6f4fe0f3ece1799a219518c2d3f6a15",
      "signal_patterns": [
        "${package}*"
      ],
      "skill_id": "cpu_profiling",
      "source": {
        "commit": "6333623a96295c1ad76e28bf1f5eb7a9ecd39864",
        "path": "backend/skills/deep/cpu_profiling.skill.yaml",
        "repository": "https://github.com/Gracker/SmartPerfetto",
        "sha256": "747b9f8972708ad1e4c8449ab8e9876c58138f44ae4f3515d87232a9173a4772"
      },
      "sql_dependencies": {
        "creates": [],
        "declared_modules": [
          "linux.cpu.frequency"
        ],
        "drops": [],
        "required_tables": [],
        "requires": [
          "_cpu_topology"
        ],
        "setup_queries": [
          "cpu_topology_view/create_topology_view"
        ]
      },
      "step_id": "core_distribution",
      "template": {
        "fragments": [],
        "parameters": [
          "min_runtime_ms",
          "package"
        ],
        "result_dependencies": []
      },
      "validation": {
        "default_execution": "capability_gate_required",
        "execution_verified": false,
        "fixtures": [],
        "runtime_compatible": null,
        "semantic_verified": false,
        "static_valid": true
      }
    },
    {
      "compatibility": {
        "android": {
          "28": {
            "reason": "No exact API semantic fixture; runtime capability proof required",
            "status": "capability_gated"
          },
          "29": {
            "reason": "No exact API semantic fixture; runtime capability proof required",
            "status": "capability_gated"
          },
          "30": {
            "reason": "No exact API semantic fixture; runtime capability proof required",
            "status": "capability_gated"
          },
          "31": {
            "reason": "No exact API semantic fixture; runtime capability proof required",
            "status": "capability_gated"
          },
          "32": {
            "reason": "No exact API semantic fixture; runtime capability proof required",
            "status": "capability_gated"
          },
          "33": {
            "reason": "No exact API semantic fixture; runtime capability proof required",
            "status": "capability_gated"
          },
          "34": {
            "reason": "No exact API semantic fixture; runtime capability proof required",
            "status": "capability_gated"
          },
          "35": {
            "reason": "No exact API semantic fixture; runtime capability proof required",
            "status": "capability_gated"
          },
          "36": {
            "reason": "No exact API semantic fixture; runtime capability proof required",
            "status": "capability_gated"
          },
          "37": {
            "reason": "No exact API semantic fixture; runtime capability proof required",
            "status": "capability_gated"
          }
        },
        "probe_capabilities": []
      },
      "id": "cpu_profiling/scheduling_latency",
      "license": {
        "origin": "smartperfetto",
        "spdx": "AGPL-3.0-or-later"
      },
      "path": "sql/cpu_profiling/scheduling_latency.sql",
      "sha256": "8c1cf9409ff09bdf3fce615e822ab0102a239f217c439056409969301640a27d",
      "signal_patterns": [
        "${package}*"
      ],
      "skill_id": "cpu_profiling",
      "source": {
        "commit": "6333623a96295c1ad76e28bf1f5eb7a9ecd39864",
        "path": "backend/skills/deep/cpu_profiling.skill.yaml",
        "repository": "https://github.com/Gracker/SmartPerfetto",
        "sha256": "747b9f8972708ad1e4c8449ab8e9876c58138f44ae4f3515d87232a9173a4772"
      },
      "sql_dependencies": {
        "creates": [],
        "declared_modules": [
          "linux.cpu.frequency"
        ],
        "drops": [],
        "required_tables": [],
        "requires": [],
        "setup_queries": []
      },
      "step_id": "scheduling_latency",
      "template": {
        "fragments": [],
        "parameters": [
          "package"
        ],
        "result_dependencies": []
      },
      "validation": {
        "default_execution": "capability_gate_required",
        "execution_verified": false,
        "fixtures": [],
        "runtime_compatible": null,
        "semantic_verified": false,
        "static_valid": true
      }
    },
    {
      "compatibility": {
        "android": {
          "28": {
            "reason": "No exact API semantic fixture; runtime capability proof required",
            "status": "capability_gated"
          },
          "29": {
            "reason": "No exact API semantic fixture; runtime capability proof required",
            "status": "capability_gated"
          },
          "30": {
            "reason": "No exact API semantic fixture; runtime capability proof required",
            "status": "capability_gated"
          },
          "31": {
            "reason": "No exact API semantic fixture; runtime capability proof required",
            "status": "capability_gated"
          },
          "32": {
            "reason": "No exact API semantic fixture; runtime capability proof required",
            "status": "capability_gated"
          },
          "33": {
            "reason": "No exact API semantic fixture; runtime capability proof required",
            "status": "capability_gated"
          },
          "34": {
            "reason": "No exact API semantic fixture; runtime capability proof required",
            "status": "capability_gated"
          },
          "35": {
            "reason": "No exact API semantic fixture; runtime capability proof required",
            "status": "capability_gated"
          },
          "36": {
            "reason": "No exact API semantic fixture; runtime capability proof required",
            "status": "capability_gated"
          },
          "37": {
            "reason": "No exact API semantic fixture; runtime capability proof required",
            "status": "capability_gated"
          }
        },
        "probe_capabilities": []
      },
      "id": "cpu_profiling/context_switches",
      "license": {
        "origin": "smartperfetto",
        "spdx": "AGPL-3.0-or-later"
      },
      "path": "sql/cpu_profiling/context_switches.sql",
      "sha256": "b1e46ea9bfcd1d6ae224a1614e3305402d9028502c2cf58ede93e40917f48309",
      "signal_patterns": [
        "${package}*"
      ],
      "skill_id": "cpu_profiling",
      "source": {
        "commit": "6333623a96295c1ad76e28bf1f5eb7a9ecd39864",
        "path": "backend/skills/deep/cpu_profiling.skill.yaml",
        "repository": "https://github.com/Gracker/SmartPerfetto",
        "sha256": "747b9f8972708ad1e4c8449ab8e9876c58138f44ae4f3515d87232a9173a4772"
      },
      "sql_dependencies": {
        "creates": [],
        "declared_modules": [
          "linux.cpu.frequency"
        ],
        "drops": [],
        "required_tables": [],
        "requires": [],
        "setup_queries": []
      },
      "step_id": "context_switches",
      "template": {
        "fragments": [],
        "parameters": [
          "package"
        ],
        "result_dependencies": []
      },
      "validation": {
        "default_execution": "capability_gate_required",
        "execution_verified": false,
        "fixtures": [],
        "runtime_compatible": null,
        "semantic_verified": false,
        "static_valid": true
      }
    },
    {
      "compatibility": {
        "android": {
          "28": {
            "reason": "No exact API semantic fixture; runtime capability proof required",
            "status": "capability_gated"
          },
          "29": {
            "reason": "No exact API semantic fixture; runtime capability proof required",
            "status": "capability_gated"
          },
          "30": {
            "reason": "No exact API semantic fixture; runtime capability proof required",
            "status": "capability_gated"
          },
          "31": {
            "reason": "No exact API semantic fixture; runtime capability proof required",
            "status": "capability_gated"
          },
          "32": {
            "reason": "No exact API semantic fixture; runtime capability proof required",
            "status": "capability_gated"
          },
          "33": {
            "reason": "No exact API semantic fixture; runtime capability proof required",
            "status": "capability_gated"
          },
          "34": {
            "reason": "No exact API semantic fixture; runtime capability proof required",
            "status": "capability_gated"
          },
          "35": {
            "reason": "No exact API semantic fixture; runtime capability proof required",
            "status": "capability_gated"
          },
          "36": {
            "reason": "No exact API semantic fixture; runtime capability proof required",
            "status": "capability_gated"
          },
          "37": {
            "reason": "No exact API semantic fixture; runtime capability proof required",
            "status": "capability_gated"
          }
        },
        "probe_capabilities": []
      },
      "id": "cpu_profiling/cpu_timeline",
      "license": {
        "origin": "smartperfetto",
        "spdx": "AGPL-3.0-or-later"
      },
      "path": "sql/cpu_profiling/cpu_timeline.sql",
      "sha256": "8a09f9eb9dbfbd72183bcc15e9c4619030015e3edd68802eca297be338141efc",
      "signal_patterns": [],
      "skill_id": "cpu_profiling",
      "source": {
        "commit": "6333623a96295c1ad76e28bf1f5eb7a9ecd39864",
        "path": "backend/skills/deep/cpu_profiling.skill.yaml",
        "repository": "https://github.com/Gracker/SmartPerfetto",
        "sha256": "747b9f8972708ad1e4c8449ab8e9876c58138f44ae4f3515d87232a9173a4772"
      },
      "sql_dependencies": {
        "creates": [],
        "declared_modules": [
          "linux.cpu.frequency"
        ],
        "drops": [],
        "required_tables": [],
        "requires": [],
        "setup_queries": []
      },
      "step_id": "cpu_timeline",
      "template": {
        "fragments": [],
        "parameters": [],
        "result_dependencies": []
      },
      "validation": {
        "default_execution": "capability_gate_required",
        "execution_verified": false,
        "fixtures": [],
        "runtime_compatible": null,
        "semantic_verified": false,
        "static_valid": true
      }
    },
    {
      "compatibility": {
        "android": {
          "28": {
            "reason": "No exact API semantic fixture; runtime capability proof required",
            "status": "capability_gated"
          },
          "29": {
            "reason": "No exact API semantic fixture; runtime capability proof required",
            "status": "capability_gated"
          },
          "30": {
            "reason": "No exact API semantic fixture; runtime capability proof required",
            "status": "capability_gated"
          },
          "31": {
            "reason": "No exact API semantic fixture; runtime capability proof required",
            "status": "capability_gated"
          },
          "32": {
            "reason": "No exact API semantic fixture; runtime capability proof required",
            "status": "capability_gated"
          },
          "33": {
            "reason": "No exact API semantic fixture; runtime capability proof required",
            "status": "capability_gated"
          },
          "34": {
            "reason": "No exact API semantic fixture; runtime capability proof required",
            "status": "capability_gated"
          },
          "35": {
            "reason": "No exact API semantic fixture; runtime capability proof required",
            "status": "capability_gated"
          },
          "36": {
            "reason": "No exact API semantic fixture; runtime capability proof required",
            "status": "capability_gated"
          },
          "37": {
            "reason": "No exact API semantic fixture; runtime capability proof required",
            "status": "capability_gated"
          }
        },
        "probe_capabilities": []
      },
      "id": "cpu_profiling/profiling_conclusion",
      "license": {
        "origin": "smartperfetto",
        "spdx": "AGPL-3.0-or-later"
      },
      "path": "sql/cpu_profiling/profiling_conclusion.sql",
      "sha256": "94d89c7a946cf2ba06992f6a76fffb1c396c2b44702031a5bdb05c4ae766096e",
      "signal_patterns": [],
      "skill_id": "cpu_profiling",
      "source": {
        "commit": "6333623a96295c1ad76e28bf1f5eb7a9ecd39864",
        "path": "backend/skills/deep/cpu_profiling.skill.yaml",
        "repository": "https://github.com/Gracker/SmartPerfetto",
        "sha256": "747b9f8972708ad1e4c8449ab8e9876c58138f44ae4f3515d87232a9173a4772"
      },
      "sql_dependencies": {
        "creates": [],
        "declared_modules": [
          "linux.cpu.frequency"
        ],
        "drops": [],
        "required_tables": [],
        "requires": [],
        "setup_queries": []
      },
      "step_id": "profiling_conclusion",
      "template": {
        "fragments": [],
        "parameters": [],
        "result_dependencies": [
          "core_distribution",
          "scheduling_latency",
          "thread_cpu_time"
        ]
      },
      "validation": {
        "default_execution": "capability_gate_required",
        "execution_verified": false,
        "fixtures": [],
        "runtime_compatible": null,
        "semantic_verified": false,
        "static_valid": true
      }
    }
  ],
  "schema_version": 1,
  "skill_id": "cpu_profiling"
}
