{
  "android": {
    "adapters": [],
    "selection_order": [
      "device_capability",
      "trace_config_and_setup_errors",
      "engine_module_and_schema",
      "target_range_row_coverage",
      "api_hint"
    ],
    "signal_patterns": [
      "${package}*"
    ]
  },
  "id": "main_thread_file_io_in_range",
  "identity": {
    "policy": "none"
  },
  "inputs": [
    {
      "description": "分析起始时间戳(ns)",
      "name": "start_ts",
      "required": true,
      "type": "timestamp"
    },
    {
      "description": "分析结束时间戳(ns)",
      "name": "end_ts",
      "required": true,
      "type": "timestamp"
    },
    {
      "description": "目标应用包名（支持 GLOB）",
      "name": "package",
      "required": false,
      "type": "string"
    },
    {
      "description": "最小切片时长阈值(ns)，默认 0.5ms",
      "name": "min_dur_ns",
      "required": false,
      "type": "integer"
    },
    {
      "description": "返回 TopK 条目，默认 10",
      "name": "top_k",
      "required": false,
      "type": "integer"
    }
  ],
  "prerequisites": {
    "modules": [],
    "required_tables": []
  },
  "query_id": "main_thread_file_io_in_range/root",
  "runtime_status": "executable",
  "schema_version": 1,
  "source": {
    "commit": "185f0ffb7335de511f608acc42f5752a0f6d7c1e",
    "path": "backend/skills/atomic/main_thread_file_io_in_range.skill.yaml",
    "sha256": "445bb9c9c1c3650896f9bc8d15f7338b57a09c8a28bc3a844cc4be55ae7e6a13"
  },
  "steps": [],
  "type": "atomic",
  "version": "1.0",
  "workflow": "io-network-media"
}
