{
  "queries": [
    {
      "compatibility": {
        "android": {
          "28": {
            "reason": "No exact API semantic fixture; runtime capability proof required",
            "status": "capability_gated"
          },
          "29": {
            "reason": "No exact API semantic fixture; runtime capability proof required",
            "status": "capability_gated"
          },
          "30": {
            "reason": "No exact API semantic fixture; runtime capability proof required",
            "status": "capability_gated"
          },
          "31": {
            "reason": "No exact API semantic fixture; runtime capability proof required",
            "status": "capability_gated"
          },
          "32": {
            "reason": "No exact API semantic fixture; runtime capability proof required",
            "status": "capability_gated"
          },
          "33": {
            "reason": "No exact API semantic fixture; runtime capability proof required",
            "status": "capability_gated"
          },
          "34": {
            "reason": "No exact API semantic fixture; runtime capability proof required",
            "status": "capability_gated"
          },
          "35": {
            "reason": "No exact API semantic fixture; runtime capability proof required",
            "status": "capability_gated"
          },
          "36": {
            "reason": "No exact API semantic fixture; runtime capability proof required",
            "status": "capability_gated"
          },
          "37": {
            "reason": "No exact API semantic fixture; runtime capability proof required",
            "status": "capability_gated"
          }
        },
        "probe_capabilities": []
      },
      "id": "android_kernel_wakelock_summary/wakelock_summary",
      "license": {
        "origin": "smartperfetto",
        "spdx": "AGPL-3.0-or-later"
      },
      "path": "sql/android_kernel_wakelock_summary/wakelock_summary.sql",
      "sha256": "1d288b9f64708d883600b3afdcc8bea682ea6ed5b098900c2e16e766990f3c05",
      "signal_patterns": [],
      "skill_id": "android_kernel_wakelock_summary",
      "source": {
        "commit": "eb4ef81e660fc397c8cabe90ab0b499899931909",
        "path": "backend/skills/atomic/android_kernel_wakelock_summary.skill.yaml",
        "repository": "https://github.com/Gracker/SmartPerfetto",
        "sha256": "b87beb54fd7e610df76952ec79d79249a37e510e08dd650fae66893a20e4af63"
      },
      "sql_dependencies": {
        "creates": [],
        "declared_modules": [
          "android.kernel_wakelocks"
        ],
        "drops": [],
        "required_tables": [],
        "requires": [],
        "setup_queries": []
      },
      "step_id": "wakelock_summary",
      "template": {
        "fragments": [],
        "parameters": [
          "end_ts",
          "start_ts"
        ],
        "result_dependencies": []
      },
      "validation": {
        "default_execution": "capability_gate_required",
        "execution_verified": false,
        "fixtures": [],
        "runtime_compatible": null,
        "semantic_verified": false,
        "static_valid": true
      }
    }
  ],
  "schema_version": 1,
  "skill_id": "android_kernel_wakelock_summary"
}
