{
  "queries": [
    {
      "compatibility": {
        "android": {
          "28": {
            "reason": "No exact API semantic fixture; runtime capability proof required",
            "status": "capability_gated"
          },
          "29": {
            "reason": "No exact API semantic fixture; runtime capability proof required",
            "status": "capability_gated"
          },
          "30": {
            "reason": "No exact API semantic fixture; runtime capability proof required",
            "status": "capability_gated"
          },
          "31": {
            "reason": "No exact API semantic fixture; runtime capability proof required",
            "status": "capability_gated"
          },
          "32": {
            "reason": "No exact API semantic fixture; runtime capability proof required",
            "status": "capability_gated"
          },
          "33": {
            "reason": "No exact API semantic fixture; runtime capability proof required",
            "status": "capability_gated"
          },
          "34": {
            "reason": "No exact API semantic fixture; runtime capability proof required",
            "status": "capability_gated"
          },
          "35": {
            "reason": "No exact API semantic fixture; runtime capability proof required",
            "status": "capability_gated"
          },
          "36": {
            "reason": "No exact API semantic fixture; runtime capability proof required",
            "status": "capability_gated"
          },
          "37": {
            "reason": "No exact API semantic fixture; runtime capability proof required",
            "status": "capability_gated"
          }
        },
        "probe_capabilities": []
      },
      "id": "frame_blocking_calls/root",
      "license": {
        "origin": "smartperfetto",
        "spdx": "AGPL-3.0-or-later"
      },
      "path": "sql/frame_blocking_calls/query.sql",
      "sha256": "394b396322e9fe298025f92b2445f23f393973237d1ac0d47f543b5e28cc4226",
      "signal_patterns": [
        "${process_name}*",
        "*Binder*",
        "*RenderThread*",
        "Binder:*",
        "RenderThread"
      ],
      "skill_id": "frame_blocking_calls",
      "source": {
        "commit": "40048058243cbb91ef11082a06ba1e4d0f7d3c5a",
        "path": "backend/skills/atomic/frame_blocking_calls.skill.yaml",
        "repository": "https://github.com/Gracker/SmartPerfetto",
        "sha256": "ee76c4261a9a7084ff1f269894e9e029305381044bfc502210772faefaf06694"
      },
      "sql_dependencies": {
        "creates": [],
        "declared_modules": [
          "android.frames.timeline",
          "android.critical_blocking_calls"
        ],
        "drops": [],
        "required_tables": [],
        "requires": [],
        "setup_queries": []
      },
      "step_id": "root",
      "template": {
        "fragments": [],
        "parameters": [
          "end_ts",
          "process_name",
          "start_ts"
        ],
        "result_dependencies": []
      },
      "validation": {
        "default_execution": "capability_gate_required",
        "execution_verified": false,
        "fixtures": [],
        "runtime_compatible": null,
        "semantic_verified": false,
        "static_valid": true
      }
    }
  ],
  "schema_version": 1,
  "skill_id": "frame_blocking_calls"
}
